LICENSE
MANIFEST.in
README.md
setup.cfg
setup.py
pcode2code/__init__.py
pcode2code/pcode2code.py
pcode2code.egg-info/PKG-INFO
pcode2code.egg-info/SOURCES.txt
pcode2code.egg-info/dependency_links.txt
pcode2code.egg-info/entry_points.txt
pcode2code.egg-info/not-zip-safe
pcode2code.egg-info/requires.txt
pcode2code.egg-info/top_level.txt
tests/Book123.xlsm
tests/Book123_EvilClippy.xlsm
tests/__init__.py
tests/integration_tests2.py
tests/output.txt
tests/output2.txt
tests/tests2.xlsm
tests/tests2_EvilClippy.xlsm
tests/tests3.xlsm
tests/tests3_EvilClippy.xlsm
tests/tests4.docm
tests/tests4_EvilClippy.docm
tests/integration/__init__.py
tests/integration/integration_tests.py
tests/integration/assert/assert
tests/integration/assert/input
tests/integration/loops/input
tests/integration/loops/loops
tests/integration/macaroni/expected
tests/integration/macaroni/macaroni
tests/integration/mal1/mal1
tests/integration/mal1/pcodedmp
tests/integration/more/input
tests/integration/more/more
tests/integration/more2/input
tests/integration/more2/more2
tests/integration/select_case/input
tests/integration/select_case/select_case
tests/see_other/tests4.docm
tests/see_other/tests4_EvilClippy.docm