Metadata-Version: 2.1
Name: pcode2code
Version: 0.1.1
Summary: a vba p-code decompiler based on pcodedmp
Home-page: https://github.com/Big5_sec/pcode2code
Author: Nicolas Zilio
Author-email: nicolas.zilio@hotmail.fr
License: GNU General Public License v3
Keywords: pcode2code
Platform: UNKNOWN
Classifier: Development Status :: 2 - Pre-Alpha
Classifier: Intended Audience :: Developers
Classifier: License :: OSI Approved :: GNU General Public License v3 (GPLv3)
Classifier: Natural Language :: English
Classifier: Programming Language :: Python :: 2
Classifier: Programming Language :: Python :: 2.7
Classifier: Programming Language :: Python :: 3
Classifier: Programming Language :: Python :: 3.5
Classifier: Programming Language :: Python :: 3.6
Classifier: Programming Language :: Python :: 3.7
Requires-Python: >=2.7, !=3.0.*, !=3.1.*, !=3.2.*, !=3.3.*, !=3.4.*
